faster_cron/__init__.py
faster_cron/async_cron.py
faster_cron/base.py
faster_cron/sync_cron.py
faster_cron-0.1.1.dist-info/METADATA
faster_cron-0.1.1.dist-info/WHEEL
faster_cron-0.1.1.dist-info/top_level.txt
faster_cron-0.1.1.dist-info/RECORD
