Metadata-Version: 2.4
Name: faster-cron
Version: 0.1.1
Summary: 一个轻量、直观、支持异步与同步双模式的定时任务调度器
Author-email: Bernard Simon <bernardziyi@gmail.com>
Project-URL: Homepage, https://github.com/BernardSimon/faster-cron
Classifier: Programming Language :: Python :: 3
Classifier: License :: OSI Approved :: MIT License
Classifier: Operating System :: OS Independent
Requires-Python: >=3.7
